./.gitignore
./PKG-INFO
./README.md
./pyproject.toml
./vision_agents/plugins/moonshine/__init__.py
./vision_agents/plugins/moonshine/stt.py
vision_agents_plugins_moonshine-0.1.9.dist-info/METADATA
vision_agents_plugins_moonshine-0.1.9.dist-info/WHEEL
vision_agents_plugins_moonshine-0.1.9.dist-info/RECORD
