Metadata-Version: 2.4
Name: vision-agents-plugins-moonshine
Version: 0.1.9
Summary: Moonshine STT integration for Vision Agents
Project-URL: Documentation, https://visionagents.ai/
Project-URL: Website, https://visionagents.ai/
Project-URL: Source, https://github.com/GetStream/Vision-Agents
License-Expression: MIT
Keywords: AI,STT,agents,moonshine,speech-to-text,transcription,voice agents
Requires-Python: >=3.10
Requires-Dist: numpy<2.3,>=2.2.6
Requires-Dist: onnxruntime>=1.22.0
Requires-Dist: soundfile>=0.13.1
Requires-Dist: vision-agents
